{
  "drug": "Acetaminophen (아세트아미노펜)",
  "generated_note": "PubMed 초록 및 FDA 라벨 기반 자동 요약 · 임상 의사결정 시 원문 확인 권장",
  "fda_summary": {
    "indications": "두통, 감기, 요통, 관절염의 경미한 통증, 치통, 근육통, 월경통의 일시적 완화 및 해열.",
    "dosage": "성인 및 12세 이상: 증상 지속 시 6시간마다 2정, 24시간 내 6정 초과 금지. 의사 지시 없이 10일 이상 복용 금지. 12세 미만은 의사 상담.",
    "warnings": [
      "간 손상 경고: 24시간 내 4,000 mg 초과 시 중증 간 손상 가능 (병용·음주자 주의).",
      "알레르기 경고: 드물게 중증 피부반응(발적·수포·발진) — 발생 시 즉시 중단·진료.",
      "간 질환자, 와파린 복용자는 사용 전 의사·약사 상담.",
      "과량 복용 시 증상이 없어도 즉시 의료기관/중독관리센터 연락."
    ]
  },
  "key_message": "최대 안전 이슈는 일관되게 간독성(과량 시). FDA 라벨(4,000 mg/일 한계)과 최신 논문(간 절편 모델의 글루타치온 고갈, 해독제 안전성)이 같은 방향을 가리킨다. 2026년 최신 연구는 임신 중 사용의 신경발달 안전성을 재평가해 ASD/ADHD와 무관하다는 안심 근거를 제시했다.",
  "papers": [
    {
      "title": "임신 중 파라세타몰 사용과 ASD/ADHD 위험",
      "journal": "JAMA Internal Medicine",
      "year": "2026",
      "pmid": "42371637",
      "purpose": "임신 중 파라세타몰 노출과 자녀의 자폐(ASD)·ADHD 위험 연관성을 형제-매칭 설계로 평가.",
      "result": "ASD(aHR 1.00)·ADHD(aHR 1.01) 모두 유의한 연관 없음. 기존 코호트의 양의 신호는 잔존 가족 교란 때문.",
      "safety": "적응증에 따른 임신 중 파라세타몰 사용 안전성에 대한 안심 근거."
    },
    {
      "title": "임신 중 사용과 신경발달 결과 (형제-매칭 연구 논평)",
      "journal": "JAMA Internal Medicine",
      "year": "2026",
      "pmid": "42371636",
      "purpose": "위 연구에 대한 동반 논평.",
      "result": "제목상 'Reassuring Evidence' — 동일 맥락의 안심 근거.",
      "safety": "임신 중 사용 안전성 재확인."
    },
    {
      "title": "Ex Vivo 인간 간 절편 배양 모델과 간독성 시험",
      "journal": "Advanced Science",
      "year": "2026",
      "pmid": "42371767",
      "purpose": "장기 생존 가능한 인간 간 절편(hPCLS-EV) 배양으로 약물유발 간손상 모델 구축.",
      "result": "아세트아미노펜에서 초기 글루타치온 고갈 등 화합물별 손상 패턴 재현.",
      "safety": "아세트아미노펜 간독성 기전(글루타치온 고갈) 연구의 실험 플랫폼."
    },
    {
      "title": "해독제 아세틸시스테인의 안전성 (의인성 과량투여 검토)",
      "journal": "Clinical Toxicology",
      "year": "2026",
      "pmid": "42370551",
      "purpose": "아세트아미노펜 중독 표준 해독제 아세틸시스테인의 투여 오류 과량투여 사례 체계적 검토.",
      "result": "16건 중 ≥1000 mg/kg 노출이 뇌부종과 유의 연관. 다단계 시스템 오류가 주원인.",
      "safety": "해독제 자체 투여 오류 위험 — 단순화된 용량 프로토콜·EMR 안전장치 필요."
    },
    {
      "title": "식물 추출물의 간보호 효과 평가",
      "journal": "Natural Product Research",
      "year": "2026",
      "pmid": "42372119",
      "purpose": "아세트아미노펜 과량 간손상(간이식 2위 원인)에 대한 식물 추출물의 간보호 잠재력 평가.",
      "result": "조추출물의 간보호 가능성 평가 (초록 일부 제공).",
      "safety": "간보호 후보물질 탐색 연구."
    }
  ]
}
